{"id":"34","age":"28","genderIdentity":"male","completedExperiments":[{"experimentType":"gesture_roll_greyscale","successfulStimuli":[{"truth":45,"value":0,"inputType":"device","sensorReading":{"duration":176,"y":0.0388794,"timestamp":1720522200,"x":0.14093,"z":0.988953,"calibration_status":1,"stability":"In motion","activity_confidence":80,"w":0.0239258,"activity":"Still"},"id":"1"},{"id":"2","inputType":"device","sensorReading":{"w":0.112183,"calibration_status":1,"z":0.816284,"activity_confidence":82,"activity":"Still","x":0.564209,"y":-0.0529785,"duration":172,"stability":"In motion","timestamp":1720522233},"value":0,"truth":41},{"truth":25,"value":0,"inputType":"device","sensorReading":{"y":-0.0455322,"activity":"Still","calibration_status":1,"duration":191,"activity_confidence":83,"timestamp":1720522242,"w":0.101807,"z":0.830383,"stability":"Stable","x":0.545898},"id":"3"},{"id":"4","truth":11,"inputType":"device","sensorReading":{"activity":"Still","y":-0.0386353,"timestamp":1720522251,"z":0.870667,"calibration_status":1,"stability":"In motion","activity_confidence":89,"w":0.108521,"x":0.478149,"duration":118},"value":0},{"id":"5","value":0,"truth":10,"sensorReading":{"activity_confidence":46,"duration":167,"y":-0.0415039,"timestamp":1720522258,"x":0.0547485,"activity":"Still","w":0.0221558,"z":0.997375,"stability":"Stable","calibration_status":1},"inputType":"device"},{"id":"6","truth":32,"inputType":"device","value":0,"sensorReading":{"calibration_status":1,"y":-0.0426636,"w":-0.0020752,"activity_confidence":75,"activity":"Still","duration":186,"stability":"In motion","z":0.997925,"x":-0.0481567,"timestamp":1720522263}},{"value":0,"inputType":"device","sensorReading":{"timestamp":1720522269,"y":-0.0250244,"calibration_status":1,"activity":"Still","activity_confidence":52,"stability":"In motion","w":0.0532837,"x":0.36499,"z":0.929138,"duration":151},"truth":37,"id":"7"},{"inputType":"device","sensorReading":{"y":-0.0968018,"stability":"In motion","timestamp":1720522279,"duration":172,"z":0.876221,"activity":"Still","activity_confidence":84,"calibration_status":1,"w":0.11676,"x":0.457397},"id":"8","value":0,"truth":35},{"value":0,"inputType":"device","sensorReading":{"activity_confidence":94,"x":0.371094,"timestamp":1720522295,"duration":190,"y":-0.0675049,"activity":"Still","calibration_status":1,"w":0.0900269,"z":0.921753,"stability":"In motion"},"truth":9,"id":"9"},{"inputType":"device","value":0,"sensorReading":{"stability":"In motion","duration":191,"activity_confidence":96,"y":-0.0534668,"w":-0.0227661,"calibration_status":1,"timestamp":1720522300,"z":0.997681,"x":-0.0352173,"activity":"Still"},"truth":16,"id":"10"},{"inputType":"device","truth":47,"sensorReading":{"activity_confidence":39,"calibration_status":1,"timestamp":1720522314,"duration":153,"z":0.939697,"y":-0.000976563,"w":0.0383301,"activity":"Still","stability":"In motion","x":0.339783},"id":"11","value":0},{"sensorReading":{"x":0.508972,"w":0.108521,"timestamp":1720522327,"activity_confidence":91,"activity":"Still","y":-0.0808105,"z":0.850098,"stability":"In motion","duration":190,"calibration_status":1},"value":0,"id":"12","truth":33,"inputType":"device"},{"value":0,"sensorReading":{"stability":"Stable","y":-0.0496216,"w":0.0774536,"z":0.884827,"x":0.456787,"timestamp":1720522348,"activity_confidence":93,"calibration_status":1,"activity":"Still","duration":148},"inputType":"device","truth":4,"id":"13"},{"inputType":"device","truth":31,"id":"14","sensorReading":{"activity":"Still","stability":"In motion","z":0.998108,"w":-0.00415039,"x":-0.0324707,"y":-0.0526123,"activity_confidence":97,"duration":185,"calibration_status":1,"timestamp":1720522354},"value":0},{"truth":42,"id":"15","inputType":"device","sensorReading":{"w":0.074585,"y":-0.0490723,"timestamp":1720522363,"duration":191,"stability":"In motion","calibration_status":1,"activity_confidence":72,"x":0.35083,"z":0.93219,"activity":"Still"},"value":0},{"truth":19,"value":0,"inputType":"device","id":"16","sensorReading":{"activity_confidence":81,"calibration_status":1,"x":0.492737,"activity":"Still","duration":153,"z":0.865112,"timestamp":1720522370,"y":-0.0466309,"stability":"In motion","w":0.0813599}},{"value":0,"inputType":"device","truth":14,"id":"17","sensorReading":{"calibration_status":1,"activity":"Still","stability":"In motion","activity_confidence":48,"x":0.258423,"z":0.962158,"w":0.0817261,"y":-0.0283203,"timestamp":1720522380,"duration":157}},{"truth":18,"inputType":"device","id":"18","sensorReading":{"w":0.0422363,"x":0.0977173,"y":-0.0189819,"duration":162,"activity":"Still","activity_confidence":81,"timestamp":1720522388,"z":0.994141,"calibration_status":1,"stability":"Stable"},"value":0},{"id":"19","truth":26,"value":0,"inputType":"device","sensorReading":{"calibration_status":1,"w":0.0584717,"duration":136,"activity_confidence":96,"timestamp":1720522398,"x":0.236206,"stability":"In motion","activity":"Still","y":6.10352e-05,"z":0.969971}},{"sensorReading":{"stability":"In motion","x":0.362549,"y":-0.0020752,"calibration_status":1,"timestamp":1720522408,"w":0.0535278,"z":0.93042,"activity":"Still","activity_confidence":97,"duration":155},"id":"20","truth":5,"value":0,"inputType":"device"}],"failedStimuli":[],"endedDate":742215209.822469,"startedDate":742214930.361162,"id":"1"},{"id":"2","startedDate":742215209.854052,"endedDate":742215393.388873,"experimentType":"gesture_roll_number","failedStimuli":[],"successfulStimuli":[{"inputType":"device","sensorReading":{"timestamp":1720522459,"w":0.0421753,"calibration_status":1,"activity_confidence":97,"activity":"Still","duration":162,"stability":"Stable","x":0.21167,"z":0.975342,"y":-0.0458374},"id":"1","truth":16,"value":0},{"id":"2","value":0,"sensorReading":{"duration":190,"z":0.950745,"x":0.302246,"calibration_status":1,"y":-0.0578003,"timestamp":1720522473,"stability":"Stable","activity_confidence":97,"w":0.0370483,"activity":"Still"},"truth":63,"inputType":"device"},{"value":0,"id":"3","sensorReading":{"activity_confidence":75,"stability":"Stable","y":-0.0710449,"activity":"Still","calibration_status":1,"duration":155,"w":0.102356,"z":0.858704,"timestamp":1720522484,"x":0.497131},"truth":91,"inputType":"device"},{"id":"4","inputType":"device","sensorReading":{"activity_confidence":84,"w":0.0930176,"x":0.462402,"duration":191,"timestamp":1720522490,"activity":"Still","calibration_status":1,"stability":"Stable","y":-0.0565796,"z":0.879944},"truth":86,"value":0},{"sensorReading":{"calibration_status":1,"w":0.0268555,"y":-0.00830078,"activity_confidence":44,"timestamp":1720522497,"activity":"Still","duration":176,"stability":"Stable","z":0.984192,"x":0.174744},"value":0,"id":"5","truth":21,"inputType":"device"},{"inputType":"device","value":0,"id":"6","sensorReading":{"y":-0.0141602,"x":0.254761,"activity":"Still","calibration_status":1,"duration":153,"timestamp":1720522502,"activity_confidence":79,"w":0.038147,"stability":"Stable","z":0.966125},"truth":36},{"truth":90,"value":0,"id":"7","sensorReading":{"x":0.514404,"timestamp":1720522508,"activity":"Still","stability":"Stable","calibration_status":1,"activity_confidence":73,"w":0.086853,"z":0.851807,"duration":164,"y":-0.0475464},"inputType":"device"},{"value":0,"inputType":"device","sensorReading":{"y":-0.0112305,"w":0.0134277,"stability":"Stable","calibration_status":1,"timestamp":1720522514,"x":0.0247192,"duration":151,"activity":"Still","z":0.999512,"activity_confidence":72},"id":"8","truth":2},{"inputType":"device","sensorReading":{"w":0.0311279,"activity":"Still","x":0.134583,"timestamp":1720522519,"y":-0.010437,"z":0.990356,"stability":"Stable","activity_confidence":60,"duration":190,"calibration_status":1},"id":"9","truth":22,"value":0},{"id":"10","inputType":"device","truth":20,"sensorReading":{"z":0.991699,"x":0.124878,"timestamp":1720522523,"w":0.029541,"y":-0.00994873,"calibration_status":1,"activity_confidence":78,"stability":"Stable","activity":"Still","duration":190},"value":0},{"id":"11","value":0,"truth":47,"inputType":"device","sensorReading":{"x":0.245483,"duration":153,"z":0.968323,"timestamp":1720522530,"activity":"Still","calibration_status":1,"stability":"Stable","w":0.0429688,"activity_confidence":89,"y":-0.0136719}},{"truth":64,"id":"12","value":0,"sensorReading":{"activity":"Still","stability":"Stable","x":0.383362,"timestamp":1720522536,"z":0.921265,"calibration_status":1,"y":-0.0291748,"w":0.059021,"activity_confidence":93,"duration":187},"inputType":"device"},{"sensorReading":{"calibration_status":1,"activity_confidence":94,"activity":"Still","duration":153,"stability":"Stable","w":0.0418091,"y":-0.0163574,"timestamp":1720522541,"z":0.959106,"x":0.27948},"inputType":"device","truth":41,"id":"13","value":0},{"truth":3,"value":0,"sensorReading":{"calibration_status":1,"w":0.015564,"y":-0.0632324,"timestamp":1720522550,"x":-0.0183105,"activity_confidence":95,"stability":"In motion","z":0.997681,"activity":"Still","duration":171},"inputType":"device","id":"14"},{"truth":42,"id":"15","sensorReading":{"duration":153,"w":0.0465698,"activity_confidence":96,"y":-0.0386963,"calibration_status":1,"stability":"Stable","activity":"Still","timestamp":1720522558,"z":0.978638,"x":0.196594},"inputType":"device","value":0},{"truth":56,"id":"16","inputType":"device","sensorReading":{"z":0.960327,"w":0.0700684,"timestamp":1720522563,"duration":155,"activity":"Still","activity_confidence":96,"x":0.266357,"stability":"Stable","y":-0.0435791,"calibration_status":1},"value":0},{"truth":51,"sensorReading":{"stability":"Stable","calibration_status":1,"w":0.0559082,"timestamp":1720522568,"x":0.227356,"activity_confidence":97,"z":0.971497,"duration":153,"activity":"Still","y":-0.0367432},"id":"17","value":0,"inputType":"device"},{"value":0,"id":"18","inputType":"device","truth":95,"sensorReading":{"calibration_status":1,"stability":"In motion","activity_confidence":59,"timestamp":1720522576,"z":0.769897,"y":-0.0810547,"x":0.616394,"duration":134,"activity":"Still","w":0.143799}},{"id":"19","value":0,"inputType":"device","sensorReading":{"activity_confidence":80,"timestamp":1720522586,"z":0.916016,"x":0.391907,"duration":163,"activity":"Still","y":-0.0322266,"calibration_status":1,"w":0.0788574,"stability":"Stable"},"truth":65},{"id":"20","truth":93,"value":0,"inputType":"device","sensorReading":{"y":-0.0404663,"calibration_status":1,"timestamp":1720522591,"x":0.48114,"activity_confidence":90,"stability":"In motion","z":0.871948,"activity":"Still","duration":155,"w":0.0807495}}]},{"startedDate":742215393.447939,"endedDate":742215548.30629,"failedStimuli":[],"successfulStimuli":[{"id":"1","inputType":"slider","value":21.23089931584245,"sensorReading":{"x":0.48114,"stability":"In motion","activity":"Still","calibration_status":1,"activity_confidence":90,"timestamp":1720522591,"y":-0.0404663,"z":0.871948,"duration":155,"w":0.0807495},"truth":8},{"truth":15,"value":0,"inputType":"slider","id":"2","sensorReading":{"z":0.871948,"activity":"Still","calibration_status":1,"timestamp":1720522591,"activity_confidence":90,"stability":"In motion","w":0.0807495,"x":0.48114,"duration":155,"y":-0.0404663}},{"sensorReading":{"activity_confidence":90,"timestamp":1720522591,"activity":"Still","calibration_status":1,"stability":"In motion","x":0.48114,"y":-0.0404663,"w":0.0807495,"z":0.871948,"duration":155},"value":13.347305321034163,"truth":38,"id":"3","inputType":"slider"},{"id":"4","sensorReading":{"x":0.48114,"y":-0.0404663,"duration":155,"w":0.0807495,"calibration_status":1,"stability":"In motion","activity":"Still","z":0.871948,"timestamp":1720522591,"activity_confidence":90},"truth":43,"value":44.56127684879216,"inputType":"slider"},{"sensorReading":{"x":0.48114,"activity_confidence":90,"duration":155,"calibration_status":1,"activity":"Still","stability":"In motion","y":-0.0404663,"z":0.871948,"timestamp":1720522591,"w":0.0807495},"id":"5","value":49,"inputType":"slider","truth":29},{"sensorReading":{"activity":"Still","timestamp":1720522591,"stability":"In motion","y":-0.0404663,"x":0.48114,"z":0.871948,"duration":155,"activity_confidence":90,"w":0.0807495,"calibration_status":1},"inputType":"slider","truth":23,"id":"6","value":37.840393307505316},{"inputType":"slider","value":23.22059592864536,"truth":1,"sensorReading":{"stability":"In motion","timestamp":1720522591,"z":0.871948,"calibration_status":1,"activity_confidence":90,"w":0.0807495,"duration":155,"activity":"Still","x":0.48114,"y":-0.0404663},"id":"7"},{"inputType":"slider","truth":40,"sensorReading":{"w":0.0807495,"z":0.871948,"activity":"Still","activity_confidence":90,"duration":155,"stability":"In motion","calibration_status":1,"y":-0.0404663,"timestamp":1720522591,"x":0.48114},"value":0,"id":"8"},{"value":42.3863789857756,"inputType":"slider","sensorReading":{"activity_confidence":90,"stability":"In motion","x":0.48114,"y":-0.0404663,"timestamp":1720522591,"calibration_status":1,"duration":155,"z":0.871948,"w":0.0807495,"activity":"Still"},"truth":24,"id":"9"},{"truth":6,"inputType":"slider","value":24.295287715015856,"sensorReading":{"timestamp":1720522591,"activity_confidence":90,"w":0.0807495,"x":0.48114,"z":0.871948,"duration":155,"calibration_status":1,"stability":"In motion","y":-0.0404663,"activity":"Still"},"id":"10"},{"value":0,"id":"11","truth":17,"inputType":"slider","sensorReading":{"activity_confidence":90,"w":0.0807495,"duration":155,"timestamp":1720522591,"y":-0.0404663,"z":0.871948,"activity":"Still","calibration_status":1,"stability":"In motion","x":0.48114}},{"inputType":"slider","id":"12","truth":36,"value":5.909601629414264,"sensorReading":{"w":0.0807495,"stability":"In motion","timestamp":1720522591,"z":0.871948,"duration":155,"x":0.48114,"y":-0.0404663,"activity":"Still","calibration_status":1,"activity_confidence":90}},{"value":32.91406695105971,"truth":3,"id":"13","inputType":"slider","sensorReading":{"z":0.871948,"timestamp":1720522591,"activity_confidence":90,"calibration_status":1,"duration":155,"w":0.0807495,"stability":"In motion","activity":"Still","x":0.48114,"y":-0.0404663}},{"id":"14","value":0,"truth":0,"inputType":"slider","sensorReading":{"z":0.871948,"duration":155,"stability":"In motion","timestamp":1720522591,"activity":"Still","calibration_status":1,"w":0.0807495,"y":-0.0404663,"activity_confidence":90,"x":0.48114}},{"value":0.7835529782930719,"sensorReading":{"w":0.0807495,"z":0.871948,"stability":"In motion","timestamp":1720522591,"activity":"Still","y":-0.0404663,"x":0.48114,"activity_confidence":90,"calibration_status":1,"duration":155},"id":"15","inputType":"slider","truth":34},{"truth":13,"inputType":"slider","id":"16","sensorReading":{"duration":155,"activity":"Still","activity_confidence":90,"z":0.871948,"w":0.0807495,"timestamp":1720522591,"x":0.48114,"y":-0.0404663,"stability":"In motion","calibration_status":1},"value":28.340055175336143},{"sensorReading":{"duration":155,"stability":"In motion","y":-0.0404663,"z":0.871948,"activity":"Still","timestamp":1720522591,"calibration_status":1,"x":0.48114,"activity_confidence":90,"w":0.0807495},"value":16.217559378620194,"truth":30,"inputType":"slider","id":"17"},{"id":"18","value":34.18046487757805,"truth":2,"inputType":"slider","sensorReading":{"activity":"Still","timestamp":1720522591,"duration":155,"activity_confidence":90,"stability":"In motion","y":-0.0404663,"w":0.0807495,"x":0.48114,"z":0.871948,"calibration_status":1}},{"truth":21,"value":1.048178771026806,"sensorReading":{"duration":155,"calibration_status":1,"w":0.0807495,"timestamp":1720522591,"y":-0.0404663,"z":0.871948,"activity":"Still","x":0.48114,"stability":"In motion","activity_confidence":90},"id":"19","inputType":"slider"},{"truth":46,"id":"20","sensorReading":{"x":0.48114,"z":0.871948,"timestamp":1720522591,"activity":"Still","duration":155,"w":0.0807495,"stability":"In motion","activity_confidence":90,"y":-0.0404663,"calibration_status":1},"value":24.06128070637724,"inputType":"slider"}],"id":"3","experimentType":"slider_greyscale"},{"id":"4","endedDate":742215813.317672,"failedStimuli":[],"startedDate":742215548.357178,"successfulStimuli":[{"id":"1","truth":5,"sensorReading":{"stability":"In motion","w":0.0807495,"x":0.48114,"y":-0.0404663,"activity":"Still","calibration_status":1,"activity_confidence":90,"duration":155,"timestamp":1720522591,"z":0.871948},"inputType":"slider","value":4.8976441704668385},{"inputType":"slider","value":33.18050683914316,"truth":28,"sensorReading":{"w":0.0807495,"calibration_status":1,"duration":155,"z":0.871948,"activity_confidence":90,"timestamp":1720522591,"activity":"Still","x":0.48114,"stability":"In motion","y":-0.0404663},"id":"2"},{"value":21.38674424961765,"sensorReading":{"activity":"Still","duration":155,"w":0.0807495,"activity_confidence":90,"calibration_status":1,"timestamp":1720522591,"stability":"In motion","x":0.48114,"y":-0.0404663,"z":0.871948},"inputType":"slider","id":"3","truth":19},{"id":"4","sensorReading":{"timestamp":1720522591,"activity":"Still","calibration_status":1,"w":0.0807495,"x":0.48114,"activity_confidence":90,"y":-0.0404663,"z":0.871948,"stability":"In motion","duration":155},"truth":37,"inputType":"slider","value":45.73170642858475},{"inputType":"slider","id":"5","truth":11,"sensorReading":{"y":-0.0404663,"z":0.871948,"duration":155,"calibration_status":1,"activity_confidence":90,"w":0.0807495,"timestamp":1720522591,"stability":"In motion","activity":"Still","x":0.48114},"value":9.847514289985732},{"inputType":"slider","truth":0,"id":"6","sensorReading":{"calibration_status":1,"activity_confidence":90,"duration":155,"w":0.0807495,"y":-0.0404663,"activity":"Still","timestamp":1720522591,"z":0.871948,"stability":"In motion","x":0.48114},"value":0},{"value":40.380673592071396,"truth":38,"id":"7","inputType":"slider","sensorReading":{"activity_confidence":90,"x":0.48114,"y":-0.0404663,"calibration_status":1,"timestamp":1720522591,"w":0.0807495,"stability":"In motion","z":0.871948,"duration":155,"activity":"Still"}},{"id":"8","inputType":"slider","sensorReading":{"activity":"Still","stability":"In motion","x":0.48114,"z":0.871948,"w":0.0807495,"timestamp":1720522591,"activity_confidence":90,"calibration_status":1,"duration":155,"y":-0.0404663},"truth":85,"value":87.59552885332737},{"sensorReading":{"timestamp":1720522591,"activity_confidence":90,"z":0.871948,"activity":"Still","stability":"In motion","calibration_status":1,"duration":155,"y":-0.0404663,"x":0.48114,"w":0.0807495},"truth":81,"inputType":"slider","id":"9","value":77.3389852143017},{"id":"10","truth":10,"value":10.186320424115468,"inputType":"slider","sensorReading":{"w":0.0807495,"duration":155,"activity_confidence":90,"activity":"Still","calibration_status":1,"stability":"In motion","timestamp":1720522591,"y":-0.0404663,"z":0.871948,"x":0.48114}},{"inputType":"slider","sensorReading":{"z":0.871948,"y":-0.0404663,"timestamp":1720522591,"activity":"Still","activity_confidence":90,"duration":155,"w":0.0807495,"x":0.48114,"calibration_status":1,"stability":"In motion"},"truth":1,"id":"11","value":0.3210838998619815},{"value":78.93717010780364,"id":"12","inputType":"slider","sensorReading":{"z":0.871948,"duration":155,"timestamp":1720522591,"activity_confidence":90,"y":-0.0404663,"activity":"Still","stability":"In motion","calibration_status":1,"x":0.48114,"w":0.0807495},"truth":76},{"sensorReading":{"activity":"Still","timestamp":1720522591,"x":0.48114,"w":0.0807495,"y":-0.0404663,"stability":"In motion","duration":155,"z":0.871948,"calibration_status":1,"activity_confidence":90},"value":53.70661349340682,"id":"13","truth":55,"inputType":"slider"},{"id":"14","sensorReading":{"stability":"In motion","timestamp":1720522591,"z":0.871948,"calibration_status":1,"activity":"Still","duration":155,"w":0.0807495,"x":0.48114,"y":-0.0404663,"activity_confidence":90},"value":13.090589358820129,"inputType":"slider","truth":15},{"value":70.47878664950761,"truth":71,"sensorReading":{"activity_confidence":90,"x":0.48114,"y":-0.0404663,"z":0.871948,"w":0.0807495,"duration":155,"timestamp":1720522591,"calibration_status":1,"activity":"Still","stability":"In motion"},"id":"15","inputType":"slider"},{"id":"16","truth":59,"sensorReading":{"x":0.48114,"y":-0.0404663,"stability":"In motion","activity_confidence":90,"activity":"Still","duration":155,"w":0.0807495,"z":0.871948,"timestamp":1720522591,"calibration_status":1},"inputType":"slider","value":58.37890115007648},{"id":"17","inputType":"slider","sensorReading":{"y":-0.0404663,"calibration_status":1,"duration":155,"activity":"Still","w":0.0807495,"x":0.48114,"z":0.871948,"timestamp":1720522591,"stability":"In motion","activity_confidence":90},"truth":6,"value":1.3658788231941026},{"id":"18","truth":79,"sensorReading":{"calibration_status":1,"w":0.0807495,"z":0.871948,"activity":"Still","y":-0.0404663,"activity_confidence":90,"stability":"In motion","duration":155,"x":0.48114,"timestamp":1720522591},"value":78.3887389025664,"inputType":"slider"},{"truth":30,"value":33.770990556690165,"sensorReading":{"activity":"Still","w":0.0807495,"timestamp":1720522591,"calibration_status":1,"duration":155,"activity_confidence":90,"z":0.871948,"stability":"In motion","x":0.48114,"y":-0.0404663},"id":"19","inputType":"slider"},{"truth":75,"value":76.27824483363175,"id":"20","inputType":"slider","sensorReading":{"w":0.0807495,"y":-0.0404663,"duration":155,"stability":"In motion","z":0.871948,"calibration_status":1,"timestamp":1720522591,"activity":"Still","activity_confidence":90,"x":0.48114}}],"experimentType":"slider_number"},{"endedDate":742216017.597125,"failedStimuli":[],"startedDate":742215813.369008,"id":"5","experimentType":"gesture_pitch_greyscale","successfulStimuli":[{"sensorReading":{"x":0.169495,"calibration_status":2,"stability":"In motion","y":0.599731,"activity_confidence":69,"duration":158,"timestamp":1720523066,"activity":"Unknown","w":0.233032,"z":0.746521},"value":0,"id":"1","inputType":"device","truth":39},{"id":"2","inputType":"device","truth":12,"value":0,"sensorReading":{"calibration_status":2,"y":0.556274,"activity_confidence":59,"stability":"In motion","z":0.567078,"activity":"Unknown","timestamp":1720523072,"duration":121,"w":0.486084,"x":0.364258}},{"sensorReading":{"x":0.0245972,"activity":"Unknown","y":0.6698,"z":0.725769,"w":0.154907,"duration":153,"timestamp":1720523091,"stability":"In motion","calibration_status":2,"activity_confidence":31},"inputType":"device","id":"3","truth":44,"value":0},{"truth":7,"value":0,"id":"4","inputType":"device","sensorReading":{"activity":"Still","calibration_status":2,"w":0.530945,"activity_confidence":72,"z":0.60437,"duration":153,"y":0.545105,"x":0.236023,"stability":"In motion","timestamp":1720523097}},{"id":"5","inputType":"device","sensorReading":{"x":-0.00354004,"y":0.639526,"timestamp":1720523105,"z":0.760559,"stability":"Stable","calibration_status":2,"duration":153,"activity":"Unknown","activity_confidence":45,"w":0.111938},"truth":48,"value":0},{"truth":22,"inputType":"device","sensorReading":{"activity_confidence":62,"duration":125,"w":0.397888,"x":0.311157,"calibration_status":2,"activity":"Unknown","stability":"Stable","z":0.608704,"timestamp":1720523112,"y":0.611816},"id":"6","value":0},{"value":0,"inputType":"device","id":"7","sensorReading":{"activity":"Still","stability":"Stable","y":0.611572,"timestamp":1720523118,"w":0.352478,"duration":176,"calibration_status":2,"x":0.168213,"activity_confidence":78,"z":0.688049},"truth":20},{"sensorReading":{"activity":"Still","w":0.397339,"z":0.696899,"x":0.088562,"timestamp":1720523121,"y":0.590454,"calibration_status":2,"stability":"Stable","activity_confidence":85,"duration":153},"inputType":"device","truth":49,"id":"8","value":0},{"id":"9","truth":19,"value":0,"inputType":"device","sensorReading":{"activity_confidence":44,"w":0.635742,"z":0.64624,"timestamp":1720523130,"x":0.0900269,"activity":"In-Vehicle","stability":"In motion","y":0.412476,"calibration_status":2,"duration":158}},{"sensorReading":{"calibration_status":2,"stability":"In motion","activity_confidence":73,"x":0.0185547,"y":0.512207,"timestamp":1720523135,"activity":"Still","duration":172,"w":0.397949,"z":0.760864},"inputType":"device","id":"10","truth":15,"value":0},{"id":"11","value":0,"inputType":"device","sensorReading":{"stability":"Stable","activity_confidence":77,"calibration_status":2,"z":0.790344,"duration":224,"activity":"Still","w":0.300415,"y":0.533569,"timestamp":1720523140,"x":-0.0203247},"truth":40},{"truth":23,"sensorReading":{"stability":"Stable","z":0.695435,"activity":"In-Vehicle","y":0.362061,"w":0.608093,"x":-0.124451,"calibration_status":2,"activity_confidence":49,"duration":185,"timestamp":1720523147},"value":0,"id":"12","inputType":"device"},{"truth":4,"sensorReading":{"stability":"In motion","duration":130,"activity":"Still","y":0.51532,"activity_confidence":72,"calibration_status":2,"w":0.377197,"x":0.0131836,"timestamp":1720523152,"z":0.769409},"id":"13","value":0,"inputType":"device"},{"value":0,"truth":28,"id":"14","inputType":"device","sensorReading":{"activity_confidence":42,"stability":"Stable","timestamp":1720523161,"activity":"Still","calibration_status":2,"y":0.616089,"duration":192,"w":0.0479736,"z":0.786011,"x":0.0189209}},{"inputType":"device","sensorReading":{"x":0.0604248,"z":0.664063,"calibration_status":2,"stability":"Stable","timestamp":1720523168,"activity":"Still","activity_confidence":75,"w":0.5,"duration":153,"y":0.552612},"truth":16,"value":0,"id":"15"},{"sensorReading":{"timestamp":1720523173,"stability":"Stable","activity_confidence":77,"z":0.746277,"w":0.365173,"duration":139,"x":-0.0358887,"y":0.555359,"calibration_status":2,"activity":"Still"},"truth":8,"id":"16","value":0,"inputType":"device"},{"id":"17","inputType":"device","truth":3,"value":0,"sensorReading":{"stability":"In motion","y":0.648193,"activity_confidence":82,"duration":157,"x":-0.0714111,"calibration_status":2,"timestamp":1720523177,"activity":"Still","z":0.739441,"w":0.167297}},{"value":0,"inputType":"device","id":"18","sensorReading":{"calibration_status":2,"stability":"In motion","duration":153,"activity_confidence":50,"x":0.0180664,"z":0.771851,"activity":"Still","w":0.0776367,"y":0.630798,"timestamp":1720523205},"truth":7},{"sensorReading":{"duration":158,"activity":"Still","z":0.766724,"y":0.625854,"calibration_status":2,"x":-0.00189209,"activity_confidence":73,"w":0.142883,"stability":"Stable","timestamp":1720523210},"inputType":"device","truth":27,"value":0,"id":"19"},{"id":"20","sensorReading":{"x":0.0777588,"y":0.540039,"timestamp":1720523215,"z":0.752686,"activity":"Still","stability":"Stable","calibration_status":2,"activity_confidence":81,"duration":162,"w":0.368469},"truth":0,"value":0,"inputType":"device"}]},{"successfulStimuli":[{"truth":99,"inputType":"device","id":"1","value":0,"sensorReading":{"x":0.277222,"activity":"In-Vehicle","timestamp":1720523274,"duration":118,"y":0.526794,"activity_confidence":63,"w":0.611816,"z":0.520935,"calibration_status":3,"stability":"In motion"}},{"sensorReading":{"y":0.694458,"timestamp":1720523289,"calibration_status":2,"w":0.164917,"activity":"Still","z":0.592468,"stability":"Stable","duration":136,"activity_confidence":51,"x":0.373535},"truth":43,"id":"2","value":0,"inputType":"device"},{"truth":58,"sensorReading":{"timestamp":1720523294,"y":0.703613,"calibration_status":2,"stability":"Stable","w":0.262146,"duration":160,"x":0.321899,"activity":"Still","activity_confidence":77,"z":0.576721},"id":"3","inputType":"device","value":0},{"truth":66,"value":0,"sensorReading":{"calibration_status":2,"w":0.31897,"x":0.41803,"y":0.644165,"z":0.555542,"stability":"Stable","duration":135,"activity_confidence":91,"timestamp":1720523304,"activity":"Still"},"id":"4","inputType":"device"},{"inputType":"device","truth":35,"value":0,"id":"5","sensorReading":{"w":0.0598145,"x":0.307129,"z":0.71875,"activity_confidence":60,"duration":209,"activity":"Walking","y":0.62085,"stability":"In motion","calibration_status":2,"timestamp":1720523310}},{"id":"6","sensorReading":{"y":0.634155,"w":0.277893,"stability":"Stable","activity_confidence":73,"z":0.684021,"timestamp":1720523316,"activity":"Still","x":0.229675,"duration":155,"calibration_status":2},"inputType":"device","value":0,"truth":70},{"sensorReading":{"duration":174,"y":0.579102,"activity":"Still","calibration_status":2,"x":0.0358887,"timestamp":1720523324,"activity_confidence":53,"z":0.801697,"w":0.143677,"stability":"In motion"},"truth":23,"id":"7","value":0,"inputType":"device"},{"id":"8","value":0,"inputType":"device","sensorReading":{"duration":153,"activity":"Still","timestamp":1720523327,"stability":"Stable","activity_confidence":81,"calibration_status":2,"w":0.0787354,"x":0.0142822,"y":0.587646,"z":0.805115},"truth":17},{"id":"9","sensorReading":{"timestamp":1720523333,"y":0.548584,"duration":155,"activity":"Unknown","activity_confidence":36,"calibration_status":3,"x":0.325378,"z":0.45105,"w":0.624268,"stability":"In motion"},"value":0,"inputType":"device","truth":100},{"truth":96,"id":"10","inputType":"device","value":0,"sensorReading":{"duration":168,"z":0.536743,"x":0.24585,"timestamp":1720523336,"activity":"Still","y":0.578003,"stability":"Stable","activity_confidence":53,"calibration_status":2,"w":0.563354}},{"inputType":"device","sensorReading":{"stability":"Stable","activity":"Still","calibration_status":2,"timestamp":1720523340,"duration":163,"y":0.621704,"activity_confidence":80,"w":0.462219,"x":0.223267,"z":0.591614},"id":"11","truth":77,"value":0},{"truth":26,"sensorReading":{"activity":"Still","calibration_status":1,"activity_confidence":85,"y":0.68866,"duration":157,"timestamp":1720523344,"w":0.0514526,"stability":"In motion","x":0.173096,"z":0.702209},"id":"12","value":0,"inputType":"device"},{"inputType":"device","truth":87,"id":"13","value":0,"sensorReading":{"stability":"In motion","z":0.603638,"activity_confidence":63,"duration":173,"calibration_status":2,"activity":"Still","timestamp":1720523350,"w":0.542908,"x":0.156799,"y":0.562378}},{"truth":25,"value":0,"id":"14","inputType":"device","sensorReading":{"activity_confidence":77,"stability":"In motion","activity":"Still","y":0.658386,"timestamp":1720523355,"calibration_status":1,"w":0.166626,"x":0.0811768,"duration":163,"z":0.729492}},{"value":0,"truth":57,"inputType":"device","sensorReading":{"duration":123,"calibration_status":2,"stability":"In motion","activity_confidence":71,"activity":"Still","w":0.423035,"x":0.064209,"y":0.57843,"z":0.694519,"timestamp":1720523360},"id":"15"},{"sensorReading":{"w":0.104919,"timestamp":1720523364,"y":0.655029,"duration":214,"stability":"In motion","activity_confidence":73,"x":0.125183,"z":0.737732,"activity":"Still","calibration_status":1},"value":0,"truth":14,"id":"16","inputType":"device"},{"value":0,"truth":40,"sensorReading":{"stability":"In motion","activity_confidence":30,"w":0.191467,"activity":"Walking","x":0.203918,"z":0.714355,"duration":134,"timestamp":1720523371,"calibration_status":2,"y":0.641479},"id":"17","inputType":"device"},{"sensorReading":{"w":0.407776,"x":0.171204,"activity_confidence":72,"y":0.570557,"stability":"In motion","calibration_status":2,"z":0.692017,"duration":158,"activity":"Still","timestamp":1720523376},"id":"18","inputType":"device","truth":83,"value":0},{"truth":4,"inputType":"device","value":0,"sensorReading":{"timestamp":1720523381,"y":0.580627,"calibration_status":2,"duration":111,"activity":"Still","z":0.801941,"activity_confidence":73,"stability":"In motion","w":0.0475464,"x":0.132263},"id":"19"},{"value":0,"sensorReading":{"activity":"Still","timestamp":1720523385,"duration":167,"calibration_status":2,"w":0.235535,"stability":"Stable","y":0.58667,"x":0.0328369,"z":0.77417,"activity_confidence":75},"truth":31,"id":"20","inputType":"device"}],"id":"6","startedDate":742216017.647195,"endedDate":742216187.385364,"experimentType":"gesture_pitch_number","failedStimuli":[]}]}